pubtools/_content_gateway/__init__.py
pubtools/_content_gateway/cgw_authentication.py
pubtools/_content_gateway/cgw_client.py
pubtools/_content_gateway/cgw_session.py
pubtools/_content_gateway/push_base.py
pubtools/_content_gateway/push_cgw.py
pubtools/_content_gateway/push_staged_cgw.py
pubtools/_content_gateway/utils.py
pubtools_content_gateway-0.5.4.dist-info/LICENSE
pubtools_content_gateway-0.5.4.dist-info/METADATA
pubtools_content_gateway-0.5.4.dist-info/WHEEL
pubtools_content_gateway-0.5.4.dist-info/entry_points.txt
pubtools_content_gateway-0.5.4.dist-info/top_level.txt
pubtools_content_gateway-0.5.4.dist-info/RECORD
