Metadata-Version: 2.1
Name: pubtools-content-gateway
Version: 0.5.4
Summary: Automate pushing to Content Gateway
Home-page: https://github.com/release-engineering/pubtools-content-gateway
Author: Javed Alam
Author-email: jalam@redhat.com
Project-URL: Changelog, https://release-engineering.github.io/pubtools-content-gateway/CHANGELOG.html
Project-URL: Documentation, https://release-engineering.github.io/pubtools-content-gateway/
Classifier: Development Status :: 3 - Alpha
Classifier: Intended Audience :: Developers
Classifier: License :: OSI Approved :: GNU Lesser General Public License v3 (LGPLv3)
Classifier: Programming Language :: Python
Classifier: Programming Language :: Python :: 3
Classifier: Programming Language :: Python :: 3.9
Classifier: Programming Language :: Python :: Implementation :: CPython
Classifier: Programming Language :: Python :: Implementation :: PyPy
Requires-Python: >=3.9
License-File: LICENSE
Requires-Dist: attrs
Requires-Dist: cffi
Requires-Dist: pycparser
Requires-Dist: urllib3
Requires-Dist: requests
Requires-Dist: setuptools
Requires-Dist: pubtools
Requires-Dist: jsonschema
Requires-Dist: pyyaml
